tfmpi2c/__init__.py
tfmpi2c/test/__init__.py
tfmpi2c/test/tfmpi2c_test.py
tfmpi2c_budryerson-0.0.5.dist-info/LICENSE
tfmpi2c_budryerson-0.0.5.dist-info/METADATA
tfmpi2c_budryerson-0.0.5.dist-info/WHEEL
tfmpi2c_budryerson-0.0.5.dist-info/top_level.txt
tfmpi2c_budryerson-0.0.5.dist-info/RECORD
